dali/__init__.py
dali/abstract_ccxt_input_plugin.py
dali/abstract_ccxt_pair_converter_plugin.py
dali/abstract_input_plugin.py
dali/abstract_pair_converter_plugin.py
dali/abstract_transaction.py
dali/cache.py
dali/ccxt_pagination.py
dali/configuration.py
dali/configuration_generator.py
dali/dali_main.py
dali/historical_bar.py
dali/in_transaction.py
dali/intra_transaction.py
dali/logger.py
dali/mapped_graph.py
dali/ods_generator.py
dali/out_transaction.py
dali/py.typed
dali/transaction_manifest.py
dali/transaction_resolver.py
dali/data/__init__.py
dali/data/template.ods
dali/plugin/__init__.py
dali/plugin/country/__init__.py
dali/plugin/country/es.py
dali/plugin/country/generic.py
dali/plugin/country/ie.py
dali/plugin/country/jp.py
dali/plugin/country/us.py
dali/plugin/input/__init__.py
dali/plugin/input/csv/__init__.py
dali/plugin/input/csv/binance_com_supplemental.py
dali/plugin/input/csv/bitbank_supplemental.py
dali/plugin/input/csv/blockfi.py
dali/plugin/input/csv/coincheck_supplemental.py
dali/plugin/input/csv/ledger.py
dali/plugin/input/csv/manual.py
dali/plugin/input/csv/nexo.py
dali/plugin/input/csv/pionex.py
dali/plugin/input/csv/trezor.py
dali/plugin/input/csv/trezor_old.py
dali/plugin/input/csv/trezor_v2.py
dali/plugin/input/ods/__init__.py
dali/plugin/input/ods/rp2_input.py
dali/plugin/input/rest/__init__.py
dali/plugin/input/rest/binance_com.py
dali/plugin/input/rest/bitbank.py
dali/plugin/input/rest/coinbase.py
dali/plugin/input/rest/coinbase_pro.py
dali/plugin/input/rest/kraken.py
dali/plugin/pair_converter/__init__.py
dali/plugin/pair_converter/ccxt.py
dali/plugin/pair_converter/ccxt_binance.py
dali/plugin/pair_converter/ccxt_coinbase_pro.py
dali/plugin/pair_converter/ccxt_exchangerate_host.py
dali/plugin/pair_converter/ccxt_fiat_from_csv.py
dali/plugin/pair_converter/ccxt_kraken.py
dali/plugin/pair_converter/historic_crypto.py
dali/plugin/pair_converter/csv/__init__.py
dali/plugin/pair_converter/csv/kraken.py
dali_rp2-0.6.11.dist-info/LICENSE
dali_rp2-0.6.11.dist-info/METADATA
dali_rp2-0.6.11.dist-info/WHEEL
dali_rp2-0.6.11.dist-info/entry_points.txt
dali_rp2-0.6.11.dist-info/top_level.txt
dali_rp2-0.6.11.dist-info/RECORD
