Metadata-Version: 2.1
Name: dali-rp2
Version: 0.6.11
Summary: Data loader and input generator for RP2 (https://pypi.org/project/rp2/), the privacy-focused, free, non-commercial, open-source, community-driven cryptocurrency tax calculator: DaLI removes the need to manually prepare RP2 input files. Just like RP2, DaLI is also free, open-source and it prioritizes user privacy.
Home-page: https://github.com/eprbell/dali-rp2
Author: eprbell
License: Apache License 2.0
Project-URL: Source Code, https://github.com/eprbell/dali-rp2
Project-URL: Developer Documentation, https://github.com/eprbell/dali-rp2/blob/main/README.dev.md
Project-URL: User Documentation, https://github.com/eprbell/dali-rp2/blob/main/README.md
Project-URL: Contact, https://eprbell.github.io/eprbell/about.html
Keywords: accounting,altcoin,bitcoin,BTC,capital gains,cost basis,crypto,cryptocurrency,data loader,DeFi,ETH,ethereum,exchange,finance,form 8949,NFT,privacy,wallet,tax
Classifier: Development Status :: 4 - Beta
Classifier: Intended Audience :: End Users/Desktop
Classifier: License :: OSI Approved :: Apache Software License
Classifier: Operating System :: OS Independent
Classifier: Programming Language :: Python :: 3.8
Classifier: Programming Language :: Python :: 3.9
Classifier: Programming Language :: Python :: 3.10
Classifier: Programming Language :: Python :: 3.11
Classifier: Programming Language :: Python :: 3.12
Classifier: Topic :: Office/Business :: Financial :: Accounting
Classifier: Topic :: Utilities
Classifier: Typing :: Typed
License-File: LICENSE
Requires-Dist: backports-datetime-fromisoformat ==2.0.0
Requires-Dist: ccxt ==3.0.79
Requires-Dist: Historic-Crypto >=0.1.6
Requires-Dist: jsonschema >=3.2.0
Requires-Dist: pandas
Requires-Dist: prezzemolo >=0.0.4
Requires-Dist: progressbar2 >=4.2.0
Requires-Dist: pyexcel-ezodf >=0.3.4
Requires-Dist: pytest-recording ==0.13.0
Requires-Dist: python-dateutil >=2.8.2
Requires-Dist: pytz >=2021.3
Requires-Dist: requests >=2.26.0
Requires-Dist: rp2 >=1.7.1
Requires-Dist: vcrpy ==4.4.0
Provides-Extra: dev
Requires-Dist: autopep8 ; extra == 'dev'
Requires-Dist: bandit ; extra == 'dev'
Requires-Dist: black ; extra == 'dev'
Requires-Dist: bumpversion ; extra == 'dev'
Requires-Dist: flake8 ; extra == 'dev'
Requires-Dist: isort ; extra == 'dev'
Requires-Dist: mypy ; extra == 'dev'
Requires-Dist: pep8 ; extra == 'dev'
Requires-Dist: pre-commit ; extra == 'dev'
Requires-Dist: pylint ; extra == 'dev'
Requires-Dist: pytest ; extra == 'dev'
Requires-Dist: pytest-mock ; extra == 'dev'
Requires-Dist: rope ; extra == 'dev'
Requires-Dist: types-jsonschema ; extra == 'dev'
Requires-Dist: types-python-dateutil ; extra == 'dev'
Requires-Dist: types-requests ; extra == 'dev'
